grepros/__init__.py
grepros/__main__.py
grepros/api.py
grepros/common.py
grepros/inputs.py
grepros/library.py
grepros/main.py
grepros/outputs.py
grepros/ros1.py
grepros/ros2.py
grepros/search.py
grepros/plugins/__init__.py
grepros/plugins/embag.py
grepros/plugins/mcap.py
grepros/plugins/parquet.py
grepros/plugins/sql.py
grepros/plugins/auto/__init__.py
grepros/plugins/auto/csv.py
grepros/plugins/auto/dbbase.py
grepros/plugins/auto/html.py
grepros/plugins/auto/html.tpl
grepros/plugins/auto/postgres.py
grepros/plugins/auto/sqlbase.py
grepros/plugins/auto/sqlite.py
grepros/vendor/__init__.py
grepros/vendor/step.py
grepros-1.2.2.dist-info/LICENSE.md
grepros-1.2.2.dist-info/METADATA
grepros-1.2.2.dist-info/WHEEL
grepros-1.2.2.dist-info/entry_points.txt
grepros-1.2.2.dist-info/top_level.txt
grepros-1.2.2.dist-info/RECORD
