Metadata-Version: 2.1
Name: grepros
Version: 1.2.2
Summary: grep for ROS bag files and live topics: read, filter, export
Home-page: https://github.com/suurjaak/grepros
Author: Erki Suurjaak
Author-email: erki@lap.ee
License: BSD
Keywords: ROS ROS1 ROS2 rosbag grep
Platform: any
Classifier: Development Status :: 5 - Production/Stable
Classifier: Environment :: Console
Classifier: Environment :: Console :: Curses
Classifier: License :: OSI Approved :: BSD License
Classifier: Intended Audience :: Developers
Classifier: Operating System :: POSIX
Classifier: Topic :: Scientific/Engineering
Classifier: Topic :: Utilities
Classifier: Programming Language :: Python :: 2
Classifier: Programming Language :: Python :: 2.7
Classifier: Programming Language :: Python :: 3
Requires-Python: >=2.7
Requires-Dist: pyyaml
Requires-Dist: six
